setup.cfg
setup.py
grove/__init__.py
grove/alpha/__init__.py
grove/alpha/arbitrary_state/__init__.py
grove/alpha/arbitrary_state/arbitrary_state.py
grove/alpha/arbitrary_state/unitary_operator.py
grove/alpha/fermion_transforms/__init__.py
grove/alpha/fermion_transforms/bktransform.py
grove/alpha/fermion_transforms/fenwick_tree.py
grove/alpha/fermion_transforms/jwtransform.py
grove/alpha/jordan_gradient/__init__.py
grove/alpha/jordan_gradient/gradient_utils.py
grove/alpha/jordan_gradient/jordan_gradient.py
grove/alpha/phaseestimation/__init__.py
grove/alpha/phaseestimation/phase_estimation.py
grove/amplification/__init__.py
grove/amplification/amplification.py
grove/amplification/grover.py
grove/amplification/oracles.py
grove/bernstein_vazirani/__init__.py
grove/bernstein_vazirani/bernstein_vazirani.py
grove/bernstein_vazirani/utils.py
grove/circuit_primitives/__init__.py
grove/circuit_primitives/swap.py
grove/deutsch_jozsa/__init__.py
grove/deutsch_jozsa/deutsch_jozsa.py
grove/ising/__init__.py
grove/ising/ising_qaoa.py
grove/measurements/__init__.py
grove/measurements/amplitude_measurement.py
grove/measurements/estimation.py
grove/measurements/term_grouping.py
grove/pyqaoa/__init__.py
grove/pyqaoa/maxcut_qaoa.py
grove/pyqaoa/numpartition_qaoa.py
grove/pyqaoa/qaoa.py
grove/pyqaoa/utils.py
grove/pyvqe/__init__.py
grove/pyvqe/vqe.py
grove/qft/__init__.py
grove/qft/fourier.py
grove/simon/__init__.py
grove/simon/simon.py
grove/simon/utils.py
grove/tomography/__init__.py
grove/tomography/operator_utils.py
grove/tomography/process_tomography.py
grove/tomography/state_tomography.py
grove/tomography/tomography.py
grove/tomography/utils.py
grove/utils/__init__.py
grove/utils/utility_programs.py
quantum_grove.egg-info/PKG-INFO
quantum_grove.egg-info/SOURCES.txt
quantum_grove.egg-info/dependency_links.txt
quantum_grove.egg-info/requires.txt
quantum_grove.egg-info/top_level.txt