Metadata-Version: 1.0
Name: quantum-grove
Version: 1.7.0
Summary: A collection of quantum algorithms built using pyQuil and Forest
Home-page: https://github.com/rigetticomputing/grove.git
Author: Rigetti Computing
Author-email: softapps@rigetti.com
License: LICENSE
Keywords: quantum quil programming hybrid
Platform: UNKNOWN
